program/Exper2_2.v
//Experiment2_2
module CODE (out,in);
	input[7:0] in;
	output[2:0] out;
	reg[2:0] out;
	always @(in)		
	case(in)
		8'b0000_0001 : out = 3'b000;
        8'b0000_0010 : out = 3'b001;
        8'b0000_0100 : out = 3'b010;
        8'b0000_1000 : out = 3'b011;
        8'b0001_0000 : out = 3'b100;
        8'b0010_0000 : out = 3'b101;
        8'b0100_0000 : out = 3'b110;
        8'b1000_0000 : out = 3'b111;
		default:out=8'bx;
	endcase
		
endmodule

module Exper2_2;
	reg [7:0]in;
	wire [2:0]out;
	CODE e2_2 (out,in);
	initial
	begin
		$dumpfile("Ex2_2.vcd");
		$dumpvars(0,e2_2);
		in[0]=0;in[1]=0;in[2]=0;in[3]=0;in[4]=0;in[5]=0;in[6]=0;in[7]=0;
		#2 in[0]=1;
		#2 in[0]=0;
		#2 in[1]=1;
		#2 in[1]=0;
		#2 in[2]=1;
		#2 in[2]=0;
		#2 in[3]=1;
		#2 in[3]=0;
		#2 in[4]=1;
		#2 in[4]=0;
		#2 in[5]=1;
		#2 in[5]=0;
		#2 in[6]=1;
		#2 in[6]=0;
		#2 in[7]=1;
		#2 in[7]=0;
		#2 $finish;
	end
endmodule

program/Ex2_2.vcd
$date
	Wed Oct 09 17:09:56 2019
$end
$version
	Icarus Verilog
$end
$timescale
	1s
$end
$scope module Exper2_2 $end
$scope module e2_2 $end
$var wire 8 ! in [7:0] $end
$var reg 3 " out [2:0] $end
$upscope $end
$upscope $end
$enddefinitions $end
#0
$dumpvars
bx "
b0 !
$end
#2
b0 "
b1 !
#4
bx "
b0 !
#6
b1 "
b10 !
#8
bx "
b0 !
#10
b10 "
b100 !
#12
bx "
b0 !
#14
b11 "
b1000 !
#16
bx "
b0 !
#18
b100 "
b10000 !
#20
bx "
b0 !
#22
b101 "
b100000 !
#24
bx "
b0 !
#26
b110 "
b1000000 !
#28
bx "
b0 !
#30
b111 "
b10000000 !
#32
bx "
b0 !
