program/Exper3_1.v
`timescale 1ns/1ps
module d_ff(
			clk,
			rst_n,
			en_n,
			din,
			q,
			q_n
            );
input clk;
input rst_n;
input en_n;
input din;

output q;
output q_n;

reg q;
reg q_n;


always@(posedge clk)
if(!en_n)
    if(!rst_n)            //Õ¨≤Ω«Â¡„
        begin
            q <= 1'b0;
            q_n <= 1'b1;
        end

    else
        begin
            q <= din;
            q_n <= ~din;
        end
	
        
endmodule

module Exper3_1;
	reg clk,cl,en_n,d;
	wire q,q_n;
	d_ff e3_1 (clk,cl,en_n,d,q,q_n);
	initial
	begin
		$dumpfile("Ex3_1.vcd");
		$dumpvars(0,e3_1);
		clk=0;en_n=0;d=0;cl=1;
		#2 clk=1;
		#2 clk=0;d=1;
		#2 clk=1;
		#2 clk=0;d=0;
		#2 clk=1;
		#2 clk=0;
		#2 clk=1;en_n=1;d=1;
		#2 clk=0;
		#2 clk=1;cl=1;d=0;
		#2 clk=0;d=1;en_n=0;
		#2 clk=1;
		#2 clk=0;en_n=0;
		#2 clk=1;cl=0;
		//#2 clk=0;
		//#2 clk=1;
		//#2 clk=0;
		#2 $finish;
	end
endmodule

program/Ex3_1.vcd
$date
	Wed Oct 23 16:21:50 2019
$end
$version
	Icarus Verilog
$end
$timescale
	1ps
$end
$scope module Exper3_1 $end
$scope module e3_1 $end
$var wire 1 ! clk $end
$var wire 1 " din $end
$var wire 1 # en_n $end
$var wire 1 $ rst_n $end
$var reg 1 % q $end
$var reg 1 & q_n $end
$upscope $end
$upscope $end
$enddefinitions $end
#0
$dumpvars
x&
x%
1$
0#
0"
0!
$end
#2000
1&
0%
1!
#4000
1"
0!
#6000
0&
1%
1!
#8000
0"
0!
#10000
1&
0%
1!
#12000
0!
#14000
1"
1#
1!
#16000
0!
#18000
0"
1!
#20000
0#
1"
0!
#22000
0&
1%
1!
#24000
0!
#26000
1&
0%
0$
1!
