program/Exper4_1.v
module CALCOMP(a,b,c,d,out);
	input a,b,c,d;
	output out;
	reg out;
always@(a or b or c or d)
	begin
		case({a,b,c,d})
		4'b0000:out=1'b1;
		4'b0001:out=1'b1;
		4'b0010:out=1'b1;
		4'b0011:out=1'b0;
		4'b0100:out=1'b1;
		4'b0101:out=1'b1;
		4'b0110:out=1'b1;
		4'b0111:out=1'b0;
		4'b1000:out=1'b1;
		4'b1001:out=1'b1;
		4'b1010:out=1'b1;
		4'b1011:out=1'b0;
		4'b1100:out=1'b0;
		4'b1101:out=1'b0;
		4'b1110:out=1'b0;
		4'b1111:out=1'b0;
		default: out=1'b0;
		endcase
	end
endmodule

`timescale 1ns/1ps
module Exper4_1; 
	reg a,b,c,d;
	wire out;
	CALCOMP e4_1(a,b,c,d,out);	 
	//initialization
	initial
	begin
		$dumpfile("Ex4_1.vcd");
		$dumpvars(0,e4_1);
		a=1'b0;b=1'b0;c=1'b0;d=1'b0;
		#20 a=1'b1;
		#20 b=1'b1;
		#20 c=1'b1;
		#20 d=1'b1;
		#20 c=1'b0;
		#20 c=1'b1;b=1'b0;
		#20 b=1'b1;a=1'b0;c=1'b0;
		#20 a=1'b1;
		#20 $finish;
	end
endmodule

program/Ex4_1.vcd
$date
	Thu Nov 07 22:21:56 2019
$end
$version
	Icarus Verilog
$end
$timescale
	1ps
$end
$scope module Exper4_1 $end
$scope module e4_1 $end
$var wire 1 ! a $end
$var wire 1 " b $end
$var wire 1 # c $end
$var wire 1 $ d $end
$var reg 1 % out $end
$upscope $end
$upscope $end
$enddefinitions $end
#0
$dumpvars
1%
0$
0#
0"
0!
$end
#20000
1!
#40000
0%
1"
#60000
1#
#80000
1$
#100000
0#
#120000
0"
1#
#140000
1%
0#
0!
1"
#160000
0%
1!
