program/Exper5_1.v
module RAM(
	input clk,
	input rst,
	input wrt,
	input rd,
	input cs,
	input [3:0] addr,
	input [3:0] data_in,
	output [3:0] data_out
	);
	
	reg [3:0] bram[15:0];
	reg [3:0] data;
	integer i;
	
	always@(posedge clk or posedge rst)
	begin
		if(rst)
		begin
		for(i=0;i<15;i++)
		bram[i]<=4'b0000;
		end
		
		else if(wrt)
		begin
		bram[addr]<=data_in;
		end
		
		else if(rd)
		begin
		data<=bram[addr];
		end
		
		else
		begin
		data<=4'hz;
		end
	end
assign data_out=data;
endmodule


module Exper5_1;
 
	reg clk,rst,wrt,rd,cs;
	reg [3:0] addr;
	reg [3:0] data_in;
	wire [3:0] data_out;
	//RAM e5_1(.clk(clk),.rst(rst),.wrt(wrt),.rd(rd),.cs(cs),.addr(addr),.data_in(data_in),.data_out(data_out)
		//	);
	RAM e5_1(clk,rst,wrt,rd,cs,addr,data_in,data_out
			);
	
	always
	begin
		#50 clk = ~clk;
	end
	 
	//initialization
	initial
	begin
		$dumpfile("Ex5_1.vcd");
		$dumpvars(0,e5_1);
		clk <= 0;
		rst <= 0;
		
		#100 cs<=1;rst<=1;wrt<=0;rd<=1;
		#200 rst<=0;addr <= 4'b0000;rd<=1;
		#200 rd<=0;wrt<=1;data_in<=4'b1010;
		#300 wrt<=0;rd<=1;
		#100 cs<=1;rst<=1;wrt<=0;rd<=1;
		#200 rst<=0;addr <= 4'b0001;rd<=1;
		#200 rd<=0;wrt<=1;data_in<=4'b1010;
		#300 wrt<=0;rd<=1;
		#100 cs<=1;rst<=1;wrt<=0;rd<=1;
		#200 rst<=0;addr <= 4'b0011;rd<=1;
		#200 rd<=0;wrt<=1;data_in<=4'b1010;
		#300 wrt<=0;rd<=1;
		#100 cs<=1;rst<=1;wrt<=0;rd<=1;
		#200 rst<=0;addr <= 4'b0101;rd<=1;
		#200 rd<=0;wrt<=1;data_in<=4'b1010;
		#300 wrt<=0;rd<=1;
		#100 cs<=1;rst<=1;wrt<=0;rd<=1;
		#200 rst<=0;addr <= 4'b0111;rd<=1;
		#200 rd<=0;wrt<=1;data_in<=4'b1010;
		#300 wrt<=0;rd<=1;
		#100 cs<=1;rst<=1;wrt<=0;rd<=1;
		#200 rst<=0;addr <= 4'b1001;rd<=1;
		#200 rd<=0;wrt<=1;data_in<=4'b1010;
		#200 wrt<=0;rd<=1;
		#300 $finish;
	end

endmodule

program/Ex5_1.vcd
$date
	Fri Nov 15 19:38:00 2019
$end
$version
	Icarus Verilog
$end
$timescale
	1s
$end
$scope module Exper5_1 $end
$scope module e5_1 $end
$var wire 4 ! addr [3:0] $end
$var wire 1 " clk $end
$var wire 1 # cs $end
$var wire 4 $ data_in [3:0] $end
$var wire 4 % data_out [3:0] $end
$var wire 1 & rd $end
$var wire 1 ' rst $end
$var wire 1 ( wrt $end
$var reg 4 ) data [3:0] $end
$var integer 32 * i [31:0] $end
$upscope $end
$upscope $end
$enddefinitions $end
#0
$dumpvars
bx *
bx )
x(
0'
x&
bx %
bx $
x#
0"
bx !
$end
#50
bz %
bz )
1"
#100
b1111 *
1&
0(
1'
1#
0"
#150
b1111 *
1"
#200
0"
#250
b1111 *
1"
#300
b0 !
0'
0"
#350
b0 %
b0 )
1"
#400
0"
#450
1"
#500
b1010 $
1(
0&
0"
#550
1"
#600
0"
#650
1"
#700
0"
#750
1"
#800
1&
0(
0"
#850
b1010 %
b1010 )
1"
#900
b1111 *
1'
0"
#950
b1111 *
1"
#1000
0"
#1050
b1111 *
1"
#1100
b1 !
0'
0"
#1150
b0 %
b0 )
1"
#1200
0"
#1250
1"
#1300
1(
0&
0"
#1350
1"
#1400
0"
#1450
1"
#1500
0"
#1550
1"
#1600
1&
0(
0"
#1650
b1010 %
b1010 )
1"
#1700
b1111 *
1'
0"
#1750
b1111 *
1"
#1800
0"
#1850
b1111 *
1"
#1900
b11 !
0'
0"
#1950
b0 %
b0 )
1"
#2000
0"
#2050
1"
#2100
1(
0&
0"
#2150
1"
#2200
0"
#2250
1"
#2300
0"
#2350
1"
#2400
1&
0(
0"
#2450
b1010 %
b1010 )
1"
#2500
b1111 *
1'
0"
#2550
b1111 *
1"
#2600
0"
#2650
b1111 *
1"
#2700
b101 !
0'
0"
#2750
b0 %
b0 )
1"
#2800
0"
#2850
1"
#2900
1(
0&
0"
#2950
1"
#3000
0"
#3050
1"
#3100
0"
#3150
1"
#3200
1&
0(
0"
#3250
b1010 %
b1010 )
1"
#3300
b1111 *
1'
0"
#3350
b1111 *
1"
#3400
0"
#3450
b1111 *
1"
#3500
b111 !
0'
0"
#3550
b0 %
b0 )
1"
#3600
0"
#3650
1"
#3700
1(
0&
0"
#3750
1"
#3800
0"
#3850
1"
#3900
0"
#3950
1"
#4000
1&
0(
0"
#4050
b1010 %
b1010 )
1"
#4100
b1111 *
1'
0"
#4150
b1111 *
1"
#4200
0"
#4250
b1111 *
1"
#4300
b1001 !
0'
0"
#4350
b0 %
b0 )
1"
#4400
0"
#4450
1"
#4500
1(
0&
0"
#4550
1"
#4600
0"
#4650
1"
#4700
1&
0(
0"
#4750
b1010 %
b1010 )
1"
