program/Exper6.v
module detectMach(data_in,clk,rst,data_out);
input data_in,clk,rst;
output data_out;
reg data_out;
reg [3:0] sta;
reg [3:0] count;
parameter 	s0=4'b1000,
			s1=4'b0100,
			s2=4'b0010,
			s3=4'b0001;
always@(sta)
	begin
	case(sta)
	s0:
	data_out=1'b0;
	s1:
	data_out=1'b0;
	s2:
	data_out=1'b0;
	s3:
	data_out=1'b1;
	default:
	data_out=1'b0;
	endcase
	end
	
always@(posedge clk or negedge rst)
	begin
	if(!rst)
	begin
	sta<=s0;
    count<=4'd0;
	end
	else
	case(sta)
	s0:
	if(data_in==1'b0) sta<=s0;
	else sta<=s1;
	s1:
	if(data_in==1'b0) sta<=s2;
	else sta<=s1;
	s2:
	if(data_in==1'b0) sta<=s0;
	else 
		begin
		sta<=s3;
		count=count+4'd1;
		end
	s3:
	if(data_in==1'b0) sta<=s1;
	else sta<=s1;
	default:
	sta<=s0;
	endcase
	end
endmodule


`timescale 1ns/1ps
module Exper6;
reg clk,rst,data_in;
wire data_out;
reg [3:0]i;


detectMach e6(
				data_in,
				clk,
				rst,				
				data_out
);
always
	begin
		#5 clk = ~clk;
	end
 
initial 
begin
$dumpfile("Ex6.vcd");
$dumpvars(0,e6);
  i=0;data_in=0;rst=0;clk=1'b0;
  #5 rst=1;
  #5 data_in=1;
  #10 data_in=0;
  #10 data_in=1;
  #10 data_in=0;
  #10 data_in=1;
  #10 data_in=0;
  #10 data_in=1;
  #10 data_in=0;
  #10 data_in=0;
  #10 data_in=1;
  #20 clk=0;  
  #30 $finish;
  
end



endmodule

program/Ex6.vcd
$date
	Sat Nov 16 14:54:12 2019
$end
$version
	Icarus Verilog
$end
$timescale
	1ps
$end
$scope module Exper6 $end
$scope module e6 $end
$var wire 1 ! clk $end
$var wire 1 " data_in $end
$var wire 1 # rst $end
$var reg 4 $ count [3:0] $end
$var reg 1 % data_out $end
$var reg 4 & sta [3:0] $end
$upscope $end
$upscope $end
$enddefinitions $end
#0
$dumpvars
b1000 &
0%
b0 $
0#
0"
0!
$end
#5000
1#
1!
#10000
1"
0!
#15000
b100 &
1!
#20000
0!
0"
#25000
b10 &
1!
#30000
0!
1"
#35000
1%
b1 &
b1 $
1!
#40000
0!
0"
#45000
0%
b100 &
1!
#50000
0!
1"
#55000
1!
#60000
0!
0"
#65000
b10 &
1!
#70000
0!
1"
#75000
1%
b1 &
b10 $
1!
#80000
0!
0"
#85000
0%
b100 &
1!
#90000
0!
#95000
b10 &
1!
#100000
0!
1"
#105000
1%
b1 &
b11 $
1!
#110000
0!
#115000
0%
b100 &
1!
