program/Exper8.v
module ALU(
	input clk,
	input signed [31:0] alu_a,//signed 表示有符号数
	input signed [31:0] alu_b,
	input 		 [4:0] alu_op,
	output [31:0]alu_out,
	output [63:0] alu_out2
	);
	reg   [31:0]alu_out;
	reg   [63:0] alu_out2;
	parameter A_NOP = 5'h00;
	parameter A_ADD = 5'h01;
	parameter A_SUB = 5'h02;
	parameter A_AND = 5'h03;
	parameter A_OR = 5'h04;
	parameter A_XOR = 5'h05;
	parameter A_NOR = 5'h06;
	parameter A_MUL = 5'h07;
	parameter A_DIV = 5'h08;
	parameter A_ROL = 5'h09;//循环左移
	
	always@(posedge clk)
	begin
	case (alu_op)
		A_NOP:alu_out = 32'b0;
		A_ADD:alu_out = alu_a+alu_b;
		A_SUB:alu_out = alu_a-alu_b;
		A_AND:alu_out = alu_a&alu_b;
		A_OR:alu_out = alu_a|alu_b;
		A_XOR:alu_out = alu_a^alu_b;
		A_NOR:alu_out = alu_a~^alu_b;
		A_MUL:alu_out2 = alu_a*alu_b;//保存在alu-out2
		A_DIV:alu_out = alu_a/alu_b;
		A_ROL:
			begin
			alu_out[31:0] = {alu_a[30:0],alu_a[31]};
			end
	endcase
	end
endmodule

module Exper8;
 
	reg [31:0] alu_a;
	reg [31:0] alu_b;
	reg clk;
	reg [4:0] alu_op;
	wire [31:0] alu_out;
	wire [63:0] alu_out2;
	ALU e8(clk,alu_a,alu_b,alu_op,alu_out,alu_out2);
	
	always
	begin
		#50 clk = ~clk;
	end
	 
	//initialization
	initial
	begin
		$dumpfile("Ex8.vcd");
		$dumpvars(0,e8);
		clk <= 1;
		
		#65  alu_a<=32'h25;alu_b<=32'h12;alu_op<=5'h01;
		#100 alu_op<=5'h09;
		#100 alu_op<=5'h02;		
		#100 alu_op<=5'h03;
		#100 alu_op<=5'h04;
		#100 alu_op<=5'h05;
		#100 alu_op<=5'h06;
		#100 alu_op<=5'h07;
		#100 alu_op<=5'h08;
		#100 alu_op<=5'h09;
		#100 $finish;
	end

endmodule

program/Ex8.vcd
$date
	Wed Dec 18 16:50:12 2019
$end
$version
	Icarus Verilog
$end
$timescale
	1s
$end
$scope module Exper8 $end
$scope module e8 $end
$var wire 32 ! alu_a [31:0] $end
$var wire 32 " alu_b [31:0] $end
$var wire 5 # alu_op [4:0] $end
$var wire 1 $ clk $end
$var reg 32 % alu_out [31:0] $end
$var reg 64 & alu_out2 [63:0] $end
$upscope $end
$upscope $end
$enddefinitions $end
#0
$dumpvars
bx &
bx %
1$
bx #
bx "
bx !
$end
#50
0$
#65
b1 #
b10010 "
b100101 !
#100
b110111 %
1$
#150
0$
#165
b1001 #
#200
b1001010 %
1$
#250
0$
#265
b10 #
#300
b10011 %
1$
#350
0$
#365
b11 #
#400
b0 %
1$
#450
0$
#465
b100 #
#500
b110111 %
1$
#550
0$
#565
b101 #
#600
1$
#650
0$
#665
b110 #
#700
b11111111111111111111111111001000 %
1$
#750
0$
#765
b111 #
#800
b1010011010 &
1$
#850
0$
#865
b1000 #
#900
b10 %
1$
#950
0$
#965
b1001 #
#1000
b1001010 %
1$
